draw_compose/__init__.py
draw_compose/draw_compose.py
draw_compose-0.0.3.dist-info/DESCRIPTION.rst
draw_compose-0.0.3.dist-info/entry_points.txt
draw_compose-0.0.3.dist-info/METADATA
draw_compose-0.0.3.dist-info/metadata.json
draw_compose-0.0.3.dist-info/RECORD
draw_compose-0.0.3.dist-info/top_level.txt
draw_compose-0.0.3.dist-info/WHEEL
