Metadata-Version: 2.0
Name: draw-compose
Version: 0.0.3
Summary: Render Docker compose files
Home-page: https://github.com/Alexis-benoist/draw-compose
Author: Alexis Benoist
Author-email: alexis.benoist@gmail.com
License: Apache License 2.0
Keywords: docker diagram render
Platform: UNKNOWN
Classifier: Development Status :: 4 - Beta
Classifier: Intended Audience :: Developers
Classifier: Programming Language :: Python :: 2
Classifier: Programming Language :: Python :: 2.7
Classifier: Programming Language :: Python :: 3
Classifier: Programming Language :: Python :: 3.3
Classifier: Programming Language :: Python :: 3.4
Classifier: Topic :: Scientific/Engineering :: Visualization
Classifier: Topic :: Software Development :: Libraries :: Python Modules
Classifier: Topic :: Database
Requires-Dist: docker-compose
Requires-Dist: pygraphviz
